interactions/ext/dynhelp/__init__.py
interactions/ext/dynhelp/extension.py
interactions_dynamic_help-1.0.4.2.dist-info/METADATA
interactions_dynamic_help-1.0.4.2.dist-info/WHEEL
interactions_dynamic_help-1.0.4.2.dist-info/top_level.txt
interactions_dynamic_help-1.0.4.2.dist-info/RECORD
